{
  "title": "Microsoft Teams",
  "slug": "openaev_teams",
  "description": "Send messages and Adaptive Cards to Microsoft Teams channels and chats via the Microsoft Graph API, for table-top exercises and crisis communication injects.",
  "short_description": "Send messages and Adaptive Cards to Microsoft Teams",
  "use_cases": ["Technical"],
  "verified": true,
  "last_verified_date": "",
  "playbook_supported": false,
  "max_confidence_level": 80,
  "support_version": "",
  "subscription_link": "https://teams.cloud.microsoft/",
  "source_code": "",
  "manager_supported": true,
  "container_version": "rolling",
  "container_image": "openaev/injector-teams",
  "container_type": "INJECTOR"
}